pytmlib/__init__.py
pytmlib/abstract_exercise.py
pytmlib/api.py
pytmlib/archiver.py
pytmlib/context.py
pytmlib/create_app.py
pytmlib/handle_error.py
pytmlib/latex.py
pytmlib/method_call_exception.py
pytmlib/serializer.py
pytmlib/output/__init__.py
pytmlib/output/abstract.py
pytmlib/output/builder.py
pytmlib/output/button.py
pytmlib/output/field.py
pytmlib/output/field_attribute.py
pytmlib/output/field_type_enum.py
pytmlib/output/figure.py
pytmlib/output/image.py
pytmlib/output/option.py
pytmlib/output/option_group.py
pytmlib/output/paragraph.py
pytmlib/output/table.py
pytmlib/output/table_cell.py
pytmlib-1.0.0.dist-info/METADATA
pytmlib-1.0.0.dist-info/WHEEL
pytmlib-1.0.0.dist-info/licenses/LICENSE
pytmlib-1.0.0.dist-info/RECORD
